twikit_ext/__init__.py
twikit_ext/client/__init__.py
twikit_ext/client/client.py
twikit_ext/client/models.py
twikit_ext/client/payloads.py
twikit_ext/client/responses.py
twikit_ext/client/v11.py
twikit_ext/enums.py
twikit_ext/models.py
twikit_ext/utils.py
twikit_ext-0.0.1.dist-info/LICENSE
twikit_ext-0.0.1.dist-info/METADATA
twikit_ext-0.0.1.dist-info/WHEEL
twikit_ext-0.0.1.dist-info/RECORD
