Metadata-Version: 2.1
Name: twikit_ext
Version: 0.0.1
Summary: Twitter api client. Extended twikit
Home-page: https://github.com/BotsForge/twikit_ext
License: MIT
Author: MrSmith06
Author-email: sletars@gmail.com
Requires-Python: >=3.8,<4.0
Classifier: License :: OSI Approved :: MIT License
Classifier: Programming Language :: Python :: 3
Classifier: Programming Language :: Python :: 3.8
Classifier: Programming Language :: Python :: 3.9
Classifier: Programming Language :: Python :: 3.10
Classifier: Programming Language :: Python :: 3.11
Classifier: Programming Language :: Python :: 3.12
Classifier: Programming Language :: Python :: 3.13
Requires-Dist: httpx (>=0.27,<0.28)
Requires-Dist: httpx-socks (>=0.9,<0.10)
Requires-Dist: loguru (>=0.7,<0.8)
Requires-Dist: proxystr (>=2.1.3,<3.0.0)
Requires-Dist: pydantic (>=2.0,<3.0)
Requires-Dist: twikit (>=2.2.0,<3.0.0)
Project-URL: Repository, https://github.com/BotsForge/twikit_ext
